graphrag_ecolink/__init__.py
graphrag_ecolink/__main__.py
graphrag_ecolink/api/__init__.py
graphrag_ecolink/api/index.py
graphrag_ecolink/api/prompt_tune.py
graphrag_ecolink/api/query.py
graphrag_ecolink/cache/__init__.py
graphrag_ecolink/cache/factory.py
graphrag_ecolink/cache/json_pipeline_cache.py
graphrag_ecolink/cache/memory_pipeline_cache.py
graphrag_ecolink/cache/noop_pipeline_cache.py
graphrag_ecolink/cache/pipeline_cache.py
graphrag_ecolink/callbacks/__init__.py
graphrag_ecolink/callbacks/blob_workflow_callbacks.py
graphrag_ecolink/callbacks/console_workflow_callbacks.py
graphrag_ecolink/callbacks/file_workflow_callbacks.py
graphrag_ecolink/callbacks/llm_callbacks.py
graphrag_ecolink/callbacks/noop_query_callbacks.py
graphrag_ecolink/callbacks/noop_workflow_callbacks.py
graphrag_ecolink/callbacks/progress_workflow_callbacks.py
graphrag_ecolink/callbacks/query_callbacks.py
graphrag_ecolink/callbacks/reporting.py
graphrag_ecolink/callbacks/workflow_callbacks.py
graphrag_ecolink/callbacks/workflow_callbacks_manager.py
graphrag_ecolink/cli/__init__.py
graphrag_ecolink/cli/index.py
graphrag_ecolink/cli/initialize.py
graphrag_ecolink/cli/main.py
graphrag_ecolink/cli/prompt_tune.py
graphrag_ecolink/cli/query.py
graphrag_ecolink/config/__init__.py
graphrag_ecolink/config/create_graphrag_config.py
graphrag_ecolink/config/defaults.py
graphrag_ecolink/config/embeddings.py
graphrag_ecolink/config/enums.py
graphrag_ecolink/config/environment_reader.py
graphrag_ecolink/config/errors.py
graphrag_ecolink/config/get_embedding_settings.py
graphrag_ecolink/config/init_content.py
graphrag_ecolink/config/load_config.py
graphrag_ecolink/config/logging.py
graphrag_ecolink/config/models/__init__.py
graphrag_ecolink/config/models/basic_search_config.py
graphrag_ecolink/config/models/cache_config.py
graphrag_ecolink/config/models/chunking_config.py
graphrag_ecolink/config/models/cluster_graph_config.py
graphrag_ecolink/config/models/community_reports_config.py
graphrag_ecolink-0.1.0.dist-info/LICENSE
graphrag_ecolink-0.1.0.dist-info/METADATA
graphrag_ecolink-0.1.0.dist-info/WHEEL
graphrag_ecolink-0.1.0.dist-info/entry_points.txt
graphrag_ecolink-0.1.0.dist-info/RECORD
