Metadata-Version: 2.3
Name: graphrag-ecolink
Version: 0.1.0
Summary: GraphRAG Ecolink: A graph-based retrieval-augmented generation (RAG) system.
License: MIT
Author: Your Name
Author-email: your@email.com
Requires-Python: >=3.10,<3.13
Classifier: License :: OSI Approved :: MIT License
Classifier: Programming Language :: Python :: 3
Classifier: Programming Language :: Python :: 3.10
Classifier: Programming Language :: Python :: 3.11
Classifier: Programming Language :: Python :: 3.12
Requires-Dist: environs (>=11.0.0,<12.0.0)
Requires-Dist: networkx (>=3.4.2,<4.0.0)
Requires-Dist: openai (>=1.68.0,<2.0.0)
Requires-Dist: pandas (>=2.2.3,<3.0.0)
Requires-Dist: tqdm (>=4.67.1,<5.0.0)
Project-URL: Source, https://github.com/yourname/graphrag-ecolink
